odoo9_addon_website_sale_suggest_create_account-9.0.1.0.0-py2.7-nspkg.pth
odoo_addons/website_sale_suggest_create_account/__openerp__.py
odoo_addons/website_sale_suggest_create_account/__init__.py
odoo_addons/website_sale_suggest_create_account/README.rst
odoo_addons/website_sale_suggest_create_account/i18n/it.po
odoo_addons/website_sale_suggest_create_account/i18n/es.po
odoo_addons/website_sale_suggest_create_account/i18n/sl.po
odoo_addons/website_sale_suggest_create_account/views/website_sale.xml
odoo_addons/website_sale_suggest_create_account/static/description/icon.png
odoo9_addon_website_sale_suggest_create_account-9.0.1.0.0.dist-info/top_level.txt
odoo9_addon_website_sale_suggest_create_account-9.0.1.0.0.dist-info/WHEEL
odoo9_addon_website_sale_suggest_create_account-9.0.1.0.0.dist-info/RECORD
odoo9_addon_website_sale_suggest_create_account-9.0.1.0.0.dist-info/metadata.json
odoo9_addon_website_sale_suggest_create_account-9.0.1.0.0.dist-info/DESCRIPTION.rst
odoo9_addon_website_sale_suggest_create_account-9.0.1.0.0.dist-info/METADATA
odoo9_addon_website_sale_suggest_create_account-9.0.1.0.0.dist-info/namespace_packages.txt
